usatt/__init__.py
usatt/_data.py
usatt/cli.py
usatt-0.0.3.dist-info/LICENSE
usatt-0.0.3.dist-info/METADATA
usatt-0.0.3.dist-info/WHEEL
usatt-0.0.3.dist-info/entry_points.txt
usatt-0.0.3.dist-info/top_level.txt
usatt-0.0.3.dist-info/RECORD
